authenticator/__init__.py
authenticator/auth_wrapper.py
authenticator/authenticator.py
bitfusion_authenticator-0.2.1.dist-info/METADATA
bitfusion_authenticator-0.2.1.dist-info/WHEEL
bitfusion_authenticator-0.2.1.dist-info/top_level.txt
bitfusion_authenticator-0.2.1.dist-info/RECORD
