Metadata-Version: 2.4
Name: bitfusion-authenticator
Version: 0.2.1
Author-email: Gleb <gleb@bitfusion.trade>
License: MIT
Requires-Python: >=3.10
Requires-Dist: python-jose[cryptography]
Requires-Dist: httpx
